<Properties StartupConfiguration="{6AB66729-BC72-4377-BD7B-AB65A9549EE1}|Default">
  <MonoDevelop.Ide.ItemProperties.Prototype.iOS PreferredExecutionTarget="MonoDevelop.IPhone.IPhoneSimulatorTarget.31ABF272-1370-4640-8096-45DF7E5D044A" />
  <MonoDevelop.Ide.Workbench ActiveDocument="Prototype/AchievementsPage.xaml">
    <Files>
      <File FileName="Prototype.iOS/Main.cs" Line="17" Column="1" />
      <File FileName="Prototype/HomePage.xaml" />
      <File FileName="Prototype/HomePage.xaml.cs" />
      <File FileName="Prototype/assets/HomePage/RemoteBar/backwhiterect2x.png" />
      <File FileName="Prototype/obj/Debug/netstandard2.0/HomePage.xaml.g.cs" />
      <File FileName="Prototype/SearchView.xaml" />
      <File FileName="Prototype/SearchView.xaml.cs" />
      <File FileName="Prototype/App.xaml.cs" />
      <File FileName="Prototype/PeoplePage.xaml" />
      <File FileName="Prototype/PeoplePage.xaml.cs" />
      <File FileName="Prototype/App.xaml" />
      <File FileName="Prototype/MainPage.xaml" />
      <File FileName="Prototype/CustomEntry.cs" />
      <File FileName="Prototype/LoginPage.xaml" />
      <File FileName="Prototype/AchievementsPage.xaml" Line="22" Column="42" />
      <File FileName="Prototype/AchievementsPage.xaml.cs" />
    </Files>
    <Pads>
      <Pad Id="ProjectPad">
        <State name="__root__">
          <Node name="Prototype" expanded="True">
            <Node name="Prototype" expanded="True">
              <Node name="assets" expanded="True">
                <Node name="Achievements" expanded="True" />
              </Node>
              <Node name="AchievementsPage.xaml" expanded="True" selected="True" />
              <Node name="App.xaml" expanded="True" />
            </Node>
          </Node>
        </State>
      </Pad>
    </Pads>
  </MonoDevelop.Ide.Workbench>
  <MonoDevelop.Ide.ItemProperties.Prototype.Android PreferredExecutionTarget="Android.SelectDevice" />
  <MonoDevelop.Ide.DebuggingService.PinnedWatches />
  <MonoDevelop.Ide.Workspace ActiveConfiguration="Debug|iPhoneSimulator" />
  <MonoDevelop.Ide.DebuggingService.Breakpoints>
    <BreakpointStore />
  </MonoDevelop.Ide.DebuggingService.Breakpoints>
  <MultiItemStartupConfigurations />
</Properties>